nonebot_plugin_mystool/__init__.py
nonebot_plugin_mystool/_version.py
nonebot_plugin_mystool/api/__init__.py
nonebot_plugin_mystool/api/common.py
nonebot_plugin_mystool/api/game_sign_api.py
nonebot_plugin_mystool/api/myb_missions_api.py
nonebot_plugin_mystool/command/__init__.py
nonebot_plugin_mystool/command/address.py
nonebot_plugin_mystool/command/common.py
nonebot_plugin_mystool/command/exchange.py
nonebot_plugin_mystool/command/help.py
nonebot_plugin_mystool/command/login.py
nonebot_plugin_mystool/command/plan.py
nonebot_plugin_mystool/command/setting.py
nonebot_plugin_mystool/command/user_check.py
nonebot_plugin_mystool/model/__init__.py
nonebot_plugin_mystool/model/common.py
nonebot_plugin_mystool/model/config.py
nonebot_plugin_mystool/model/data.py
nonebot_plugin_mystool/model/upgrade/__init__.py
nonebot_plugin_mystool/model/upgrade/common.py
nonebot_plugin_mystool/model/upgrade/configV2.py
nonebot_plugin_mystool/model/upgrade/dataV2.py
nonebot_plugin_mystool/utils/__init__.py
nonebot_plugin_mystool/utils/common.py
nonebot_plugin_mystool/utils/good_image.py
nonebot_plugin_mystool-2.10.1.dist-info/LICENSE
nonebot_plugin_mystool-2.10.1.dist-info/METADATA
nonebot_plugin_mystool-2.10.1.dist-info/WHEEL
nonebot_plugin_mystool-2.10.1.dist-info/RECORD
