Metadata-Version: 2.3
Name: nonebot-plugin-mystool
Version: 2.10.1
Summary: QQ聊天、频道机器人插件 | 米游社工具-每日米游币任务、游戏签到、商品兑换、免抓包登录、原神崩铁便笺提醒
License: MIT
Keywords: bot,qq,qqbot,onebotv11,onebot,nonebot2,nonebot,mihoyo,mihoyobbs,qq-guild,star-rail,genshin-impact
Author: Ljzd-PRO
Author-email: me@ljzd.link
Requires-Python: >=3.9,<4.0
Classifier: Development Status :: 5 - Production/Stable
Classifier: License :: OSI Approved :: MIT License
Classifier: Operating System :: OS Independent
Classifier: Programming Language :: Python :: 3
Classifier: Programming Language :: Python :: 3.9
Classifier: Programming Language :: Python :: 3.10
Classifier: Programming Language :: Python :: 3.11
Classifier: Programming Language :: Python :: 3.12
Classifier: Programming Language :: Python :: 3.13
Requires-Dist: Pillow (>=9.5,<12.0)
Requires-Dist: httpx (>=0.24.1,<0.29.0)
Requires-Dist: nonebot-adapter-onebot (>=2.3.1,<3.0.0)
Requires-Dist: nonebot-adapter-qq (>=1.1.2,<2.0.0)
Requires-Dist: nonebot-plugin-send-anything-anywhere (>=0.5,<0.8)
Requires-Dist: nonebot2 (>=2.0.0)
Requires-Dist: nonebot_plugin_apscheduler (>=0.2.0)
Requires-Dist: ntplib (>=0.4.0,<0.5.0)
Requires-Dist: pydantic (>=1.10.14,<2.0.0)
Requires-Dist: pytz (>=2023.4,<2025.0)
Requires-Dist: qrcode (>=7.4.2,<9.0.0)
Requires-Dist: requests (>=2.31.0,<3.0.0)
Requires-Dist: tenacity (>=8.2.3,<10.0.0)
Project-URL: Bug Tracker, https://github.com/Ljzd-PRO/nonebot-plugin-mystool/issues
Project-URL: Documentation, https://github.com/Ljzd-PRO/nonebot-plugin-mystool/wiki
Project-URL: Homepage, https://github.com/Ljzd-PRO/nonebot-plugin-mystool
Project-URL: Repository, https://github.com/Ljzd-PRO/nonebot-plugin-mystool
